mcp_neo4j_data_modeling/__init__.py
mcp_neo4j_data_modeling/data_model.py
mcp_neo4j_data_modeling/models.py
mcp_neo4j_data_modeling/server.py
mcp_neo4j_data_modeling/static.py
mcp_neo4j_data_modeling/utils.py
mcp_neo4j_data_modeling-0.8.2.dist-info/METADATA
mcp_neo4j_data_modeling-0.8.2.dist-info/WHEEL
mcp_neo4j_data_modeling-0.8.2.dist-info/entry_points.txt
mcp_neo4j_data_modeling-0.8.2.dist-info/RECORD
