Metadata-Version: 2.4
Name: mcp-neo4j-data-modeling
Version: 0.8.2
Summary: A simple Neo4j MCP server for creating graph data models.
Requires-Python: <4.0,>=3.10
Requires-Dist: fastmcp>=2.0.0
Requires-Dist: pydantic>=2.10.1
Requires-Dist: rdflib>=7.0.0
Requires-Dist: starlette>=0.47.0
